nameko_keycloak/__init__.py
nameko_keycloak/auth.py
nameko_keycloak/dependencies.py
nameko_keycloak/fakes.py
nameko_keycloak/py.typed
nameko_keycloak/service.py
nameko_keycloak/types.py
nameko_keycloak-2.2.0.dist-info/licenses/LICENSE
nameko_keycloak-2.2.0.dist-info/WHEEL
nameko_keycloak-2.2.0.dist-info/METADATA
nameko_keycloak-2.2.0.dist-info/RECORD
