Metadata-Version: 2.4
Name: nameko-keycloak
Version: 2.2.0
Summary: Helpers to integrate Single Sign-On in nameko-based applications using Keycloak.
Author: Emplocity
License-Expression:  Apache-2.0
License-File: LICENSE
Classifier: Development Status :: 3 - Alpha
Classifier: Intended Audience :: Developers
Classifier: Operating System :: Unix
Classifier: Operating System :: POSIX
Classifier: Programming Language :: Python
Classifier: Programming Language :: Python :: 3
Classifier: Programming Language :: Python :: 3.10
Classifier: Programming Language :: Python :: 3.11
Classifier: Programming Language :: Python :: 3.12
Classifier: Programming Language :: Python :: 3.13
Classifier: Programming Language :: Python :: 3.14
Classifier: Programming Language :: Python :: Implementation :: CPython
Classifier: Topic :: Utilities
Requires-Dist: nameko>=3.0rc11
Requires-Dist: jwcrypto>=1.5
Requires-Dist: python-keycloak>=4.2
Requires-Dist: werkzeug>=2.0
Requires-Dist: pytest>=8 ; extra == 'test'
Requires-Python: >=3.10
Project-URL: Changelog, https://nameko-keycloak.readthedocs.io/en/latest/changelog.html
Project-URL: Documentation, https://nameko-keycloak.readthedocs.io/
Project-URL: Homepage, https://github.com/Emplocity/nameko-keycloak
Project-URL: Issue Tracker, https://github.com/Emplocity/nameko-keycloak/issues
Provides-Extra: test
